{
	"name": "SourceDataset_63o",
	"properties": {
		"linkedServiceName": {
			"referenceName": "AzureDataLakeStorage1",
			"type": "LinkedServiceReference"
		},
		"annotations": [],
		"type": "Excel",
		"typeProperties": {
			"sheetName": "Master",
			"location": {
				"type": "AzureBlobFSLocation",
				"fileName": "Employee+Master.xlsx",
				"fileSystem": "powerbicontainer"
			}
		},
		"schema": [
			{
				"type": "String"
			},
			{
				"type": "String"
			},
			{
				"type": "String"
			},
			{
				"type": "String"
			},
			{
				"type": "String"
			},
			{
				"type": "String"
			},
			{
				"type": "String"
			},
			{
				"type": "String"
			},
			{
				"type": "String"
			}
		]
	}
}